{
  "document_type": "VIC_AUS_DRIVER_LICESE",
  "issuing_country": "AUS",
  "issuing_state": "VIC",
  "full_name": "MICHAEL THORNTON",
  "first_name": "SUSAN",
  "middle_name": null,
  "last_name": "WASHINGTON",
  "unit": "UNIT 4",
  "street": "SUITE 303 67 DAKOTA SUBWAY",
  "suburb": "HURLEYTOWN",
  "state": "VIC",
  "postcode": "2978",
  "full_address": "UNIT 4, 12 BELLBIRD CRESCENT, RESERVOIR VIC 3073",
  "licence_number": "190975329",
  "card_number": "D2298393",
  "licence_type": "CAR",
  "conditions": "S",
  "condition_description": "Corrective lenses to be worn while driving",
  "expiry_date": "11-08-2027",
  "date_of_birth": "05-06-1974",
  "dob_watermark": "11081985",
  "age_indicator": "-83",
  "barcode_number": "ABnoteNZ8723543755",
  "notice_text": "VicRoads must be notified of your CHANGE OF ADDRESS by visiting www.vicroads.vic.gov.au or telephoning 131171 or writing to PO Box 777 Carlton Sth 3053"
}